fulladder/halfadd.v
module halfadd (
    a,b,sum,cout
);

input wire a, b;
output cout;
output [1:0] sum;

assign cout = a*b;
assign sum = a^b;
    
endmodule

fulladder/full_tb.v
`timescale 1ns/1ns

module full_tb;
    initial begin
        $dumpfile("full_tb.vcd");
        $dumpvars(0,full_tb);
    end
//xor = sum and and = cout
    reg  a_tb , b_tb, c_tb;
    wire cout1_tb, cout2_tb, cout_tb;
    wire [1:0] sum1_tb, sum2_tb;
    wire sum_tb;

    halfadd halfadd1
    (
        .a(a_tb),
        .b(b_tb),
        .cout(cout1_tb),
        .sum(sum1_tb)
    );
    halfadd halfadd2(
        .a(sum1_tb[0]),
        .b(c_tb),
        .cout(cout2_tb),
        .sum(sum2_tb)
    );

    assign cout_tb = cout1_tb | cout2_tb;
    assign sum_tb = sum2_tb;
    initial begin
        a_tb = 1'b0;
        b_tb = 1'b0;
        c_tb = 1'b0;
        #5
        a_tb = 1'b0;
        b_tb = 1'b1;
        c_tb = 1'b0;
        #5
        a_tb = 1'b1;
        b_tb = 1'b0;
        c_tb = 1'b0;
        #5
        a_tb = 1'b1;
        b_tb = 1'b1;
        c_tb = 1'b0;
        #5
        a_tb = 1'b0;
        b_tb = 1'b0;
        c_tb = 1'b1;
        #5
        a_tb = 1'b0;
        b_tb = 1'b1;
        c_tb = 1'b1;
        #5
        a_tb = 1'b1;
        b_tb = 1'b0;
        c_tb = 1'b1;
        #5
        a_tb = 1'b1;
        b_tb = 1'b1;
        c_tb = 1'b1;
        #40
        $display("Test Completed!");
        $finish;
    end

endmodule

fulladder/full_tb.vcd
$date
	Thu May  6 01:03:08 2021
$end
$version
	Icarus Verilog
$end
$timescale
	1ns
$end
$scope module full_tb $end
$var wire 1 ! cout_tb $end
$var wire 1 " sum_tb $end
$var wire 2 # sum2_tb [1:0] $end
$var wire 2 $ sum1_tb [1:0] $end
$var wire 1 % cout2_tb $end
$var wire 1 & cout1_tb $end
$var reg 1 ' a_tb $end
$var reg 1 ( b_tb $end
$var reg 1 ) c_tb $end
$scope module halfadd1 $end
$var wire 1 ' a $end
$var wire 1 ( b $end
$var wire 2 * sum [1:0] $end
$var wire 1 & cout $end
$upscope $end
$scope module halfadd2 $end
$var wire 1 + a $end
$var wire 1 ) b $end
$var wire 2 , sum [1:0] $end
$var wire 1 % cout $end
$upscope $end
$upscope $end
$enddefinitions $end
#0
$dumpvars
b0 ,
0+
b0 *
0)
0(
0'
0&
0%
b0 $
b0 #
0"
0!
$end
#5
1"
b1 #
b1 ,
1+
b1 $
b1 *
1(
#10
0(
0&
1'
#15
0"
b0 #
b0 ,
0+
1!
b0 $
b0 *
1&
1(
#20
1"
b1 #
b1 ,
0!
1)
0(
0&
0'
#25
0"
1!
b0 #
b0 ,
1%
1+
b1 $
b1 *
1(
#30
0(
0&
1'
#35
1"
b1 #
b1 ,
0%
0+
b0 $
b0 *
1&
1(
